kindps.py
kindps-0.1.0.dist-info/entry_points.txt
kindps-0.1.0.dist-info/LICENSE
kindps-0.1.0.dist-info/WHEEL
kindps-0.1.0.dist-info/METADATA
kindps-0.1.0.dist-info/RECORD
