Metadata-Version: 2.3
Name: kindps
Version: 0.1.0
Summary: Find host PIDs for processes in Kind cluster
Keywords: kubernetes,kind
Author-email: Tero Saarni <tero.saarni@gmail.com>
Requires-Python: >=3.9
Classifier: License :: OSI Approved :: Apache Software License
Classifier: Operating System :: POSIX :: Linux
Project-URL: Documentation, https://github.com/tsaarni/kind-ps
Project-URL: Source, https://github.com/tsaarni/kind-ps
